setup.py
Orange_OPTIMIZATION.egg-info/PKG-INFO
Orange_OPTIMIZATION.egg-info/SOURCES.txt
Orange_OPTIMIZATION.egg-info/dependency_links.txt
Orange_OPTIMIZATION.egg-info/entry_points.txt
Orange_OPTIMIZATION.egg-info/namespace_packages.txt
Orange_OPTIMIZATION.egg-info/top_level.txt
orangecontrib/__init__.py
orangecontrib/optimization/__init__.py
orangecontrib/optimization/widgets/Extract_domain.py
orangecontrib/optimization/widgets/Optimizer_optuna.py
orangecontrib/optimization/widgets/__init__.py
orangecontrib/optimization/widgets/icons/extract.png
orangecontrib/optimization/widgets/widget_designer/Extract_domain.ui