Metadata-Version: 2.1
Name: Orange-OPTIMIZATION
Version: 0.0.23
Summary: Let's Optimize !
Home-page: 
Author: 
Author-email: 
Keywords: orange3 add-on
